pyrandomtools/Pipfile
pyrandomtools/__init__.py
pyrandomtools/aws_functions.py
pyrandomtools/functions.py
pyrandomtools-0.1.3.dist-info/LICENSE
pyrandomtools-0.1.3.dist-info/WHEEL
pyrandomtools-0.1.3.dist-info/METADATA
pyrandomtools-0.1.3.dist-info/RECORD
