Metadata-Version: 2.1
Name: pyrandomtools
Version: 0.1.3
Summary: Random python functions organized into a module
Home-page: http://github.com/rickalm/pyrandomtools
License: MIT
Author: Rick Alm
Author-email: rickealm@gmail.com
Requires-Python: >=3.6,<4.0
Classifier: License :: OSI Approved :: MIT License
Classifier: Programming Language :: Python :: 3
Classifier: Programming Language :: Python :: 3.6
Classifier: Programming Language :: Python :: 3.7
Requires-Dist: boto3 (>=1.9,<2.0)
Project-URL: Repository, http://github.com/rickalm/pyrandomtools
